zdg/Dockerfile
zdg/__init__.py
zdg/compose_dgraph.py
zdg/compose_dgraph.yml
zdg/create_venv.sh
zdg/node_demo.py
zdg/node_demo.sh
zdg/node_interface.py
zdg-0.0.15.dist-info/METADATA
zdg-0.0.15.dist-info/WHEEL
zdg-0.0.15.dist-info/licenses/LICENSE
zdg-0.0.15.dist-info/RECORD
